eskiz_sms/__init__.py
eskiz_sms/admin.py
eskiz_sms/apps.py
eskiz_sms/models.py
eskiz_sms/urls.py
eskiz_sms/views.py
eskiz_sms/migrations/0001_initial.py
eskiz_sms/migrations/__init__.py
eskiz_sms/templates/send_sms.html
django_eskiz_sms-0.1.6.dist-info/LICENSE
django_eskiz_sms-0.1.6.dist-info/METADATA
django_eskiz_sms-0.1.6.dist-info/WHEEL
django_eskiz_sms-0.1.6.dist-info/top_level.txt
django_eskiz_sms-0.1.6.dist-info/RECORD
