Metadata-Version: 2.1
Name: django-eskiz-sms
Version: 0.1.6
Summary: Djangoda Eskiz.Uz API orqali SMS yuborish uchun eng mukammal paket
Home-page: https://github.com/Otajonov/django-eskiz-sms
Author: Ro'zmat Otajonov
Author-email: hello@tijorat.org
Maintainer: Ro'zmat Otajonov
Maintainer-email: hello@tijorat.org
License: MIT
Project-URL: Yordam, https://t.me/RozmatOtajonov
Project-URL: GitHub Soure Code, https://github.com/Otajonov/django-eskiz-sms
Classifier: Development Status :: 5 - Production/Stable
Classifier: Environment :: Web Environment
Classifier: Intended Audience :: Developers
Classifier: License :: OSI Approved :: MIT License
Classifier: Operating System :: OS Independent
Classifier: Framework :: Django
Classifier: Framework :: Django :: 3.2
Classifier: Framework :: Django :: 4.0
Classifier: Framework :: Django :: 4.1
Classifier: Framework :: Django :: 4.2
Classifier: Framework :: Django :: 5.0
Classifier: Programming Language :: Python
Classifier: Programming Language :: Python :: 3
Classifier: Programming Language :: Python :: 3.7
Classifier: Programming Language :: Python :: 3.8
Classifier: Programming Language :: Python :: 3.9
Classifier: Programming Language :: Python :: 3.10
Classifier: Programming Language :: Python :: 3.11
Classifier: Programming Language :: Python :: 3.12
Requires-Python: >=3.7
License-File: LICENSE
Requires-Dist: Django >=3.2
Requires-Dist: requests
